{
  "kind": "implementation_plan",
  "version": "1.0",
  "title": "Update Stories content with Bengali story and refresh contact email",
  "requirements": [
    {
      "id": "REQ-1",
      "summary": "Replace the Stories (গল্প) placeholder article with the provided Bengali story titled “আশ্রয়হীন”, preserving full body text and readable paragraph formatting while keeping the existing comments component intact.",
      "acceptanceCriteria": [
        "When navigating to the Stories/গল্প section, the article title displays exactly as “আশ্রয়হীন”.",
        "The story body text is rendered in full and matches the user-provided Bengali text (no omissions or edits).",
        "The story is formatted for readability (e.g., paragraph breaks preserved; no collapsed single-block text).",
        "The existing Stories section comments component remains present and functional."
      ],
      "file_operations": [
        {
          "path": "frontend/src/App.tsx",
          "operation": "modify",
          "description": "In the Stories section UI, replace “Sample Story Title” with the exact Bengali title “আশ্রয়হীন” and replace the placeholder paragraphs with the full user-provided Bengali story body text. Implement rendering that preserves paragraph breaks for readability (e.g., render from a multi-line string without trimming/rewrapping the content). Ensure the existing <CommentsSection section=\"stories\" /> remains present and wired exactly as before."
        }
      ]
    },
    {
      "id": "REQ-2",
      "summary": "Update the Contact section email display and mailto link to shovangoswami6@gmail.com.",
      "acceptanceCriteria": [
        "The Contact section shows “shovangoswami6@gmail.com” as the email text.",
        "Clicking the email opens a mailto link targeting “shovangoswami6@gmail.com”.",
        "No remaining UI text in the Contact section references the old email address."
      ],
      "file_operations": [
        {
          "path": "frontend/src/components/ContactSection.tsx",
          "operation": "modify",
          "description": "Update the static email card to display “shovangoswami6@gmail.com” and change the anchor href to \"mailto:shovangoswami6@gmail.com\". Verify no other Contact section UI strings still reference the previous email address."
        }
      ]
    }
  ]
}